tigernet/__init__.py
tigernet/_version.py
tigernet/generate_data.py
tigernet/info.py
tigernet/stats.py
tigernet/tigernet.py
tigernet/utils.py
tigernet/tests/__init__.py
tigernet/tests/network_objects.py
tigernet/tests/test_cost_matrix.py
tigernet/tests/test_data_generation.py
tigernet/tests/test_errors.py
tigernet/tests/test_info.py
tigernet/tests/test_kdtree.py
tigernet/tests/test_obs2obs_empirical.py
tigernet/tests/test_obs2obs_synthetic.py
tigernet/tests/test_observations_empirical.py
tigernet/tests/test_observations_synthetic.py
tigernet/tests/test_stats.py
tigernet/tests/test_tigernet_empirical_gdf.py
tigernet/tests/test_tigernet_empirical_shp.py
tigernet/tests/test_tigernet_synthetic.py
tigernet/tests/test_utils.py
tigernet-0.2.9.dist-info/LICENSE.txt
tigernet-0.2.9.dist-info/METADATA
tigernet-0.2.9.dist-info/WHEEL
tigernet-0.2.9.dist-info/top_level.txt
tigernet-0.2.9.dist-info/RECORD
