Metadata-Version: 2.1
Name: tigernet
Version: 0.2.9
Summary: Network Topology via TIGER/Line Edges
Home-page: https://github.com/jGaboardi/tigernet
Maintainer: James D. Gaboardi
Maintainer-email: jgaboardi@gmail.com
License: 3-Clause BSD
Download-URL: https://pypi.org/project/tigernet
Keywords: network-topology,tiger-line,python,graph-theory
Platform: UNKNOWN
Classifier: Development Status :: 4 - Beta
Classifier: Intended Audience :: Science/Research
Classifier: Intended Audience :: Developers
Classifier: Intended Audience :: Education
Classifier: Topic :: Scientific/Engineering
Classifier: Topic :: Scientific/Engineering :: GIS
Classifier: License :: OSI Approved :: BSD License
Classifier: Programming Language :: Python
Classifier: Programming Language :: Python :: 3.8
Classifier: Programming Language :: Python :: 3.9
Classifier: Programming Language :: Python :: 3.10
Requires-Python: >=3.8
License-File: LICENSE.txt
Requires-Dist: black
Requires-Dist: gdal (>=3.3.0)
Requires-Dist: geopandas (>=0.9.0)
Requires-Dist: libpysal
Requires-Dist: numpy
Requires-Dist: pandas
Requires-Dist: pre-commit
Requires-Dist: pygeos (>=0.8)
Requires-Dist: shapely (>=1.7.1)
Requires-Dist: spaghetti
Requires-Dist: codecov
Requires-Dist: pytest
Requires-Dist: pytest-cov
Requires-Dist: pytest-xdist
